numeric_diff/__init__.py
numeric_diff/first_second_numeric_diff.py
numeric_diff-1.0.0.dist-info/LICENSE
numeric_diff-1.0.0.dist-info/METADATA
numeric_diff-1.0.0.dist-info/WHEEL
numeric_diff-1.0.0.dist-info/top_level.txt
numeric_diff-1.0.0.dist-info/RECORD
