Metadata-Version: 2.2
Name: numeric_diff
Version: 1.0.0
Summary: This Python package containts functions that do numeric differentiation.
Author-email: Juan David Amaya Carreño <jd.amaya20@uniandes.edu.co>
Classifier: Programming Language :: Python :: 3
Classifier: Operating System :: Microsoft :: Windows
Classifier: License :: OSI Approved :: MIT License
Requires-Python: >=3.10
License-File: LICENSE
